Metadata-Version: 2.1
Name: aspecto-ot-auto-instrumentation
Version: 0.1.dev2
Summary: Aspecto Auto Instrumentation for OpenTelemetry
Home-page: https://app.aspecto.io
Author: Aspecto
Author-email: nir@aspecto.io
License: Apache-2.0
Platform: any
Classifier: Development Status :: 4 - Beta
Classifier: Intended Audience :: Developers
Classifier: License :: OSI Approved :: Apache Software License
Classifier: Programming Language :: Python
Classifier: Programming Language :: Python :: 3
Classifier: Programming Language :: Python :: 3.4
Classifier: Programming Language :: Python :: 3.5
Classifier: Programming Language :: Python :: 3.6
Classifier: Programming Language :: Python :: 3.7
Classifier: Programming Language :: Python :: 3.8
Requires-Python: >=3.4
